MANIFEST.in
README.md
gpolyencode.py
pyproject.toml
setup.py
tox.ini
py_gpolyencode.egg-info/PKG-INFO
py_gpolyencode.egg-info/SOURCES.txt
py_gpolyencode.egg-info/dependency_links.txt
py_gpolyencode.egg-info/top_level.txt
tests/test_data.txt
tests/test_gpolyencode.py