Metadata-Version: 2.1
Name: py-gpolyencode
Version: 0.2.1
Summary: Google Maps Polyline encoding (pure Python)
Home-page: http://code.google.com/p/py-gpolyencode/
Author: Robert Coup
Author-email: Robert Coup <robert.coup@koordinates.com>
Project-URL: Homepage, https://github.com/codesyntax/py-gpolyencode
Project-URL: Documentation, https://github.com/codesyntax/py-gpolyencode/blob/master/README.md
Project-URL: Repository, https://github.com/codesyntax/py-gpolyencode
Project-URL: Bug Tracker, https://github.com/codesyntax/py-gpolyencode/issues
Keywords: gis,geospatial,google-maps,gmaps,mapping
Classifier: Development Status :: 4 - Beta
Classifier: Environment :: Web Environment
Classifier: License :: OSI Approved :: BSD License
Classifier: Intended Audience :: Developers
Classifier: Operating System :: OS Independent
Classifier: Programming Language :: Python
Classifier: Topic :: Scientific/Engineering :: GIS
Classifier: Topic :: Utilities
Provides: gpolyencode
